hospitalpy/Evaluator.py
hospitalpy/Tokenizer.py
hospitalpy/__init__.py
hospitalpy/config.py
hospitalpy/sandbox.py
hospitalpy/assets/__init__.py
hospitalpy/assets/test.jsonl
hospitalpy/assets/translation_table.clinical_diagnosis.final.json
hospitalpy-0.1.324.dist-info/LICENSE
hospitalpy-0.1.324.dist-info/METADATA
hospitalpy-0.1.324.dist-info/WHEEL
hospitalpy-0.1.324.dist-info/top_level.txt
hospitalpy-0.1.324.dist-info/RECORD
