Metadata-Version: 2.1
Name: hospitalpy
Version: 0.1.324
Summary: Text Regularization for Unstructured Text from EMS Reports
Author: Michael Chary
Author-email: "M. Anand Chary" <mic9189@med.cornell.edu>
License: Copyright (c) 2018 The Python Packaging Authority
Project-URL: Homepage, https://github.com/mac389/base-hospitalpy
Project-URL: Issues, https://github.com/mac389/base-hospitalpy/issues
Keywords: NLP,Text Regularization,EMS Reports
Requires-Python: >=3.11
License-File: LICENSE
Requires-Dist: pandas
Requires-Dist: regex
